another_jira_cli-0.17.0.dist-info/DESCRIPTION.rst
another_jira_cli-0.17.0.dist-info/METADATA
another_jira_cli-0.17.0.dist-info/RECORD
another_jira_cli-0.17.0.dist-info/WHEEL
another_jira_cli-0.17.0.dist-info/entry_points.txt
another_jira_cli-0.17.0.dist-info/metadata.json
another_jira_cli-0.17.0.dist-info/top_level.txt
jira_cli/__init__.py
jira_cli/__main__.py
jira_cli/jirahelpers.py
jira_cli/parsehelpers.py
jira_cli/tools.py
jira_cli/workloghelpers.py
