Metadata-Version: 2.0
Name: another-jira-cli
Version: 0.17.0
Summary: A cli tool for JIRA useful for time tracking and bulk ticket creation.
Home-page: https://github.com/CognotektGmbH/python-jira-cli
Author: Axel Bock
Author-email: mr.axel.bock@gmail.com
License: UNKNOWN
Download-URL: https://github.com/CognotektGmbH/python-jira-cli/tarball/0.17.0
Keywords: jira cli
Platform: UNKNOWN
Classifier: License :: OSI Approved :: MIT License
Classifier: Development Status :: 4 - Beta
Classifier: Intended Audience :: Developers
Classifier: Intended Audience :: System Administrators
Classifier: Intended Audience :: End Users/Desktop
Classifier: Programming Language :: Python :: 3
Classifier: Operating System :: POSIX
Classifier: Operating System :: MacOS
Requires-Dist: jira
Requires-Dist: click
Requires-Dist: arrow
Requires-Dist: PyYAML
Requires-Dist: dotmap
Requires-Dist: pbr
Requires-Dist: python-editor
